ansible_rulebook/__init__.py
ansible_rulebook/__main__.py
ansible_rulebook/app.py
ansible_rulebook/cli.py
ansible_rulebook/collection.py
ansible_rulebook/common.py
ansible_rulebook/condition_parser.py
ansible_rulebook/condition_types.py
ansible_rulebook/conf.py
ansible_rulebook/engine.py
ansible_rulebook/exception.py
ansible_rulebook/job_template_runner.py
ansible_rulebook/json_generator.py
ansible_rulebook/messages.py
ansible_rulebook/rule_generator.py
ansible_rulebook/rule_set_runner.py
ansible_rulebook/rule_types.py
ansible_rulebook/rules_parser.py
ansible_rulebook/terminal.py
ansible_rulebook/token.py
ansible_rulebook/util.py
ansible_rulebook/validators.py
ansible_rulebook/vault.py
ansible_rulebook/websocket.py
ansible_rulebook/action/__init__.py
ansible_rulebook/action/control.py
ansible_rulebook/action/debug.py
ansible_rulebook/action/helper.py
ansible_rulebook/action/metadata.py
ansible_rulebook/action/noop.py
ansible_rulebook/action/pg_notify.py
ansible_rulebook/action/post_event.py
ansible_rulebook/action/print_event.py
ansible_rulebook/action/retract_fact.py
ansible_rulebook/action/run_job_template.py
ansible_rulebook/action/run_module.py
ansible_rulebook/action/run_playbook.py
ansible_rulebook/action/run_workflow_template.py
ansible_rulebook/action/runner.py
ansible_rulebook/action/set_fact.py
ansible_rulebook/action/shutdown.py
ansible_rulebook/event_filter/__init__.py
ansible_rulebook/event_filter/event_splitter.py
ansible_rulebook/event_filter/insert_meta_info.py
ansible_rulebook/schema/ruleset_schema.json
ansible_rulebook-1.2.0.dist-info/licenses/LICENSE
ansible_rulebook-1.2.0.dist-info/METADATA
ansible_rulebook-1.2.0.dist-info/WHEEL
ansible_rulebook-1.2.0.dist-info/entry_points.txt
ansible_rulebook-1.2.0.dist-info/top_level.txt
ansible_rulebook-1.2.0.dist-info/RECORD
