Metadata-Version: 2.4
Name: ansible_rulebook
Version: 1.2.0
Summary: Event driven automation for Ansible
Home-page: https://github.com/ansible/ansible-rulebook
License: Apache-2.0
Keywords: ansible_rulebook
Classifier: Development Status :: 5 - Production/Stable
Classifier: Intended Audience :: Developers
Classifier: License :: OSI Approved :: Apache Software License
Classifier: Natural Language :: English
Classifier: Programming Language :: Python :: 3
Classifier: Programming Language :: Python :: 3.9
Classifier: Programming Language :: Python :: 3.10
Classifier: Programming Language :: Python :: 3.11
Classifier: Programming Language :: Python :: 3.12
Requires-Python: >=3.9
License-File: LICENSE
Requires-Dist: aiohttp<3.11,>=3
Requires-Dist: pyparsing<4,>=3.0
Requires-Dist: jsonschema<5,>=4
Requires-Dist: jinja2<4,>=3
Requires-Dist: dpath<3,>=2.1.4
Requires-Dist: janus<2,>=1
Requires-Dist: ansible-runner<3,>=2
Requires-Dist: websockets<15.1,>=15
Requires-Dist: drools_jpy==0.3.14
Requires-Dist: watchdog<7,>=3
Requires-Dist: xxhash<4,>=3
Requires-Dist: pyyaml<7,>=6
Requires-Dist: psycopg[binary]<4,>=3
Provides-Extra: production
Requires-Dist: psycopg[c]<4,>=3; extra == "production"
Provides-Extra: development
Requires-Dist: psycopg[binary]<4,>=3; extra == "development"
Dynamic: license-file
